pymodaq_plugins_hinds/__init__.py
pymodaq_plugins_hinds/utils.py
pymodaq_plugins_hinds/app/__init__.py
pymodaq_plugins_hinds/app/custom_app_template.py
pymodaq_plugins_hinds/daq_move_plugins/__init__.py
pymodaq_plugins_hinds/daq_move_plugins/daq_move_PEM200.py
pymodaq_plugins_hinds/daq_viewer_plugins/__init__.py
pymodaq_plugins_hinds/daq_viewer_plugins/plugins_0D/__init__.py
pymodaq_plugins_hinds/daq_viewer_plugins/plugins_0D/daq_0Dviewer_Template.py
pymodaq_plugins_hinds/daq_viewer_plugins/plugins_1D/__init__.py
pymodaq_plugins_hinds/daq_viewer_plugins/plugins_1D/daq_1Dviewer_Template.py
pymodaq_plugins_hinds/daq_viewer_plugins/plugins_2D/__init__.py
pymodaq_plugins_hinds/daq_viewer_plugins/plugins_2D/daq_2Dviewer_Template.py
pymodaq_plugins_hinds/daq_viewer_plugins/plugins_ND/__init__.py
pymodaq_plugins_hinds/exporters/__init__.py
pymodaq_plugins_hinds/extensions/__init__.py
pymodaq_plugins_hinds/extensions/custom_extension_template.py
pymodaq_plugins_hinds/hardware/__init__.py
pymodaq_plugins_hinds/hardware/pem200_driver.py
pymodaq_plugins_hinds/models/PIDModelTemplate.py
pymodaq_plugins_hinds/models/__init__.py
pymodaq_plugins_hinds/resources/VERSION
pymodaq_plugins_hinds/resources/__init__.py
pymodaq_plugins_hinds/resources/config_template.toml
pymodaq_plugins_hinds/scanners/__init__.py
pymodaq_plugins_hinds-0.0.3.dist-info/LICENSE
pymodaq_plugins_hinds-0.0.3.dist-info/METADATA
pymodaq_plugins_hinds-0.0.3.dist-info/WHEEL
pymodaq_plugins_hinds-0.0.3.dist-info/entry_points.txt
pymodaq_plugins_hinds-0.0.3.dist-info/top_level.txt
pymodaq_plugins_hinds-0.0.3.dist-info/RECORD
