Metadata-Version: 2.1
Name: pymodaq-plugins-hinds
Version: 0.0.3
Summary: PyMoDaq plugins for instruments from Hinds Instruments
Home-page: https://github.com/NanoQM/pymodaq_plugins_hinds
Author: Daichi Kozawa
Author-email: kozawa.daichi@nims.go.jp
License: MIT
Classifier: Programming Language :: Python :: 3
Classifier: Development Status :: 5 - Production/Stable
Classifier: Environment :: Other Environment
Classifier: Intended Audience :: Science/Research
Classifier: Topic :: Scientific/Engineering :: Human Machine Interfaces
Classifier: Topic :: Scientific/Engineering :: Visualization
Classifier: License :: OSI Approved :: MIT License
Classifier: Operating System :: OS Independent
Classifier: Topic :: Software Development :: Libraries :: Python Modules
Classifier: Topic :: Software Development :: User Interfaces
License-File: LICENSE
Requires-Dist: toml
Requires-Dist: pymodaq>=4.3.6
Requires-Dist: pyvisa
